star_toffee-1.0.0.dist-info/licenses/LICENSE
toffee/__init__.py
toffee/get_tess_orbit.py
toffee/main.py
toffee/tests/__init__.py
toffee/tests/test_toffee.py
star_toffee-1.0.0.dist-info/METADATA
star_toffee-1.0.0.dist-info/WHEEL
star_toffee-1.0.0.dist-info/top_level.txt
star_toffee-1.0.0.dist-info/RECORD
