Metadata-Version: 2.4
Name: star_toffee
Version: 1.0.0
Summary: Package for finding flares in TESS lightcurves
Author-email: Jason Reeves <jasonree702@gmail.com>
License-Expression: MIT
Project-URL: Homepage, https://github.com/JasonReeves702/TOFFEE/blob/main/README.md
Project-URL: Issues, https://github.com/JasonReeves702/TOFFEE/issues
Classifier: Programming Language :: Python :: 3
Classifier: Operating System :: OS Independent
Requires-Python: >=3.8
License-File: LICENSE
Dynamic: license-file
